MANIFEST.in
README.md
requirements.txt
setup.py
kanjinetworks/__init__.py
kanjinetworks/kanji.py
kanjinetworks.egg-info/PKG-INFO
kanjinetworks.egg-info/SOURCES.txt
kanjinetworks.egg-info/dependency_links.txt
kanjinetworks.egg-info/not-zip-safe
kanjinetworks.egg-info/requires.txt
kanjinetworks.egg-info/top_level.txt
kanjinetworks/data/.DS_Store
kanjinetworks/data/etymologicaldictionaryofhanchinesecharacters-160816005400.pdf
kanjinetworks/data/etymologicaldictionaryofhanchinesecharacters-160816005400.txt
kanjinetworks/data/test.japanese
kanjinetworks/export/__init__.py
kanjinetworks/export/japaneseapp.py
kanjinetworks/extract/__init__.py
kanjinetworks/extract/extractor.py
kanjinetworks/extract/parser.py
scripts/kn_to_ja.py