Metadata-Version: 1.1
Name: kanjinetworks
Version: 0.1.8
Summary: Kanji Networks interface
Home-page: https://github.com/acoomans/kanjinetworks
Author: Arnaud Coomans
Author-email: arnaud.coomans@gmail.com
License: MIT
Download-URL: https://github.com/acoomans/kanjinetworks/archive/master.zip
Platform: UNKNOWN
